spin/__init__.py
spin/backend.py
spin/config.py
spin/device.py
spin/nicos.py
spin/pils.py
spin/secop.py
spin/server.py
spin/tango.py
spin/utils.py
spin/assets/__init__.py
spin/assets/chart-luxon.js
spin/assets/chart-timestack.js
spin/assets/chart-zoom.js
spin/assets/chart.js
spin/assets/control.svg
spin/assets/error.svg
spin/assets/filesaver.js
spin/assets/hammer.js
spin/assets/icon.png
spin/assets/info.svg
spin/assets/keyboard.css
spin/assets/keyboard.js
spin/assets/locked.svg
spin/assets/logo.svg
spin/assets/luxon.js
spin/assets/mlz.svg
spin/assets/page.html
spin/assets/pico.min.css
spin/assets/pils-table.js
spin/assets/refresh.svg
spin/assets/spin.css
spin/assets/spin.js
spin/assets/sprintf.js
spin/assets/sync.svg
spin/plugins/__init__.py
spin/plugins/lakeshore/__init__.py
spin/plugins/lakeshore/lakeshore.css
spin/plugins/lakeshore/lakeshore.js
spin_hmi-0.9.2.dist-info/METADATA
spin_hmi-0.9.2.dist-info/WHEEL
spin_hmi-0.9.2.dist-info/entry_points.txt
spin_hmi-0.9.2.dist-info/top_level.txt
spin_hmi-0.9.2.dist-info/RECORD
