Metadata-Version: 2.4
Name: spin-hmi
Version: 0.9.2
Summary: Control box monitoring system
Author-email: Georg Brandl <g.brandl@fz-juelich.de>, Enrico Faulhaber <enrico.faulhaber@frm2.tum.de>, Alexander Zaft <a.zaft@fz-juelich.de>
License: GPL-2.0-or-later
Classifier: Development Status :: 4 - Beta
Classifier: Intended Audience :: Developers
Classifier: Intended Audience :: Science/Research
Classifier: Natural Language :: English
Classifier: Operating System :: OS Independent
Classifier: Programming Language :: Python
Classifier: Programming Language :: Python :: 3
Classifier: Topic :: Scientific/Engineering
Classifier: Topic :: Scientific/Engineering :: Human Machine Interfaces
Requires-Python: >=3.9
Requires-Dist: aiohttp
Requires-Dist: mlzlog
Requires-Dist: zapf
Provides-Extra: tango
Requires-Dist: pytango>=9.3; extra == "tango"
